package net.wolfesoftware.jax.codegen;

public interface Instructions
{
    byte nop = 0;
    byte aconst_null = 1;
    byte iconst_m1 = 2;
    byte iconst_0 = 3;
    byte iconst_1 = 4;
    byte iconst_2 = 5;
    byte iconst_3 = 6;
    byte iconst_4 = 7;
    byte iconst_5 = 8;
    byte lconst_0 = 9;
    byte lconst_1 = 10;
    byte fconst_0 = 11;
    byte fconst_1 = 12;
    byte fconst_2 = 13;
    byte dconst_0 = 14;
    byte dconst_1 = 15;
    byte bipush = 16;
    byte sipush = 17;
    byte ldc = 18;
    byte ldc_w = 19;
    byte ldc2_w = 20;
    byte iload = 21;
    byte lload = 22;
    byte fload = 23;
    byte dload = 24;
    byte aload = 25;
    byte iload_0 = 26;
    byte iload_1 = 27;
    byte iload_2 = 28;
    byte iload_3 = 29;
    byte lload_0 = 30;
    byte lload_1 = 31;
    byte lload_2 = 32;
    byte lload_3 = 33;
    byte fload_0 = 34;
    byte fload_1 = 35;
    byte fload_2 = 36;
    byte fload_3 = 37;
    byte dload_0 = 38;
    byte dload_1 = 39;
    byte dload_2 = 40;
    byte dload_3 = 41;
    byte aload_0 = 42;
    byte aload_1 = 43;
    byte aload_2 = 44;
    byte aload_3 = 45;
    byte iaload = 46;
    byte laload = 47;
    byte faload = 48;
    byte daload = 49;
    byte aaload = 50;
    byte baload = 51;
    byte caload = 52;
    byte saload = 53;
    byte istore = 54;
    byte lstore = 55;
    byte fstore = 56;
    byte dstore = 57;
    byte astore = 58;
    byte istore_0 = 59;
    byte istore_1 = 60;
    byte istore_2 = 61;
    byte istore_3 = 62;
    byte lstore_0 = 63;
    byte lstore_1 = 64;
    byte lstore_2 = 65;
    byte lstore_3 = 66;
    byte fstore_0 = 67;
    byte fstore_1 = 68;
    byte fstore_2 = 69;
    byte fstore_3 = 70;
    byte dstore_0 = 71;
    byte dstore_1 = 72;
    byte dstore_2 = 73;
    byte dstore_3 = 74;
    byte astore_0 = 75;
    byte astore_1 = 76;
    byte astore_2 = 77;
    byte astore_3 = 78;
    byte iastore = 79;
    byte lastore = 80;
    byte fastore = 81;
    byte dastore = 82;
    byte aastore = 83;
    byte bastore = 84;
    byte castore = 85;
    byte sastore = 86;
    byte pop = 87;
    byte pop2 = 88;
    byte dup = 89;
    byte dup_x1 = 90;
    byte dup_x2 = 91;
    byte dup2 = 92;
    byte dup2_x1 = 93;
    byte dup2_x2 = 94;
    byte swap = 95;
    byte iadd = 96;
    byte ladd = 97;
    byte fadd = 98;
    byte dadd = 99;
    byte isub = 100;
    byte lsub = 101;
    byte fsub = 102;
    byte dsub = 103;
    byte imul = 104;
    byte lmul = 105;
    byte fmul = 106;
    byte dmul = 107;
    byte idiv = 108;
    byte ldiv = 109;
    byte fdiv = 110;
    byte ddiv = 111;
    byte irem = 112;
    byte lrem = 113;
    byte frem = 114;
    byte drem = 115;
    byte ineg = 116;
    byte lneg = 117;
    byte fneg = 118;
    byte dneg = 119;
    byte ishl = 120;
    byte lshl = 121;
    byte ishr = 122;
    byte lshr = 123;
    byte iushr = 124;
    byte lushr = 125;
    byte iand = 126;
    byte land = 127;
    byte ior = (byte)128;
    byte lor = (byte)129;
    byte ixor = (byte)130;
    byte lxor = (byte)131;
    byte iinc = (byte)132;
    byte i2l = (byte)133;
    byte i2f = (byte)134;
    byte i2d = (byte)135;
    byte l2i = (byte)136;
    byte l2f = (byte)137;
    byte l2d = (byte)138;
    byte f2i = (byte)139;
    byte f2l = (byte)140;
    byte f2d = (byte)141;
    byte d2i = (byte)142;
    byte d2l = (byte)143;
    byte d2f = (byte)144;
    byte i2b = (byte)145;
    byte i2c = (byte)146;
    byte i2s = (byte)147;
    byte lcmp = (byte)148;
    byte fcmpl = (byte)149;
    byte fcmpg = (byte)150;
    byte dcmpl = (byte)151;
    byte dcmpg = (byte)152;
    byte ifeq = (byte)153;
    byte ifne = (byte)154;
    byte iflt = (byte)155;
    byte ifge = (byte)156;
    byte ifgt = (byte)157;
    byte ifle = (byte)158;
    byte if_icmpeq = (byte)159;
    byte if_icmpne = (byte)160;
    byte if_icmplt = (byte)161;
    byte if_icmpge = (byte)162;
    byte if_icmpgt = (byte)163;
    byte if_icmple = (byte)164;
    byte if_acmpeq = (byte)165;
    byte if_acmpne = (byte)166;
    byte _goto = (byte)167;
    byte jsr = (byte)168;
    byte ret = (byte)169;
    byte tableswitch = (byte)170;
    byte lookupswitch = (byte)171;
    byte ireturn = (byte)172;
    byte lreturn = (byte)173;
    byte freturn = (byte)174;
    byte dreturn = (byte)175;
    byte areturn = (byte)176;
    byte _return = (byte)177;
    byte getstatic = (byte)178;
    byte putstatic = (byte)179;
    byte getfield = (byte)180;
    byte putfield = (byte)181;
    byte invokevirtual = (byte)182;
    byte invokespecial = (byte)183;
    byte invokestatic = (byte)184;
    byte invokeinterface = (byte)185;
    byte invokedynamic = (byte)186;
    byte _new = (byte)187;
    byte newarray = (byte)188;
    byte anewarray = (byte)189;
    byte arraylength = (byte)190;
    byte athrow = (byte)191;
    byte checkcast = (byte)192;
    byte _instanceof = (byte)193;
    byte monitorenter = (byte)194;
    byte monitorexit = (byte)195;
    byte wide = (byte)196;
    byte multianewarray = (byte)197;
    byte ifnull = (byte)198;
    byte ifnonnull = (byte)199;
    byte goto_w = (byte)200;
    byte jsr_w = (byte)201;
    byte breakpoint = (byte)202;
}
